src/__init__.py
my_orm.py
src/SQL/__init__.py
src/SQL/manager.py
src/SQL/sql_commands_alter_table.py
src/SQL/sql_commands_cond.py
src/SQL/sql_commands_create.py
src/SQL/sql_commands_prop.py
src/utils/__init__.py
src/utils/convert.py
src/utils/validate.py
src/utils/verify_tags.py
my_orm_py-1.2.dist-info/METADATA
my_orm_py-1.2.dist-info/WHEEL
my_orm_py-1.2.dist-info/RECORD
