Metadata-Version: 2.1
Name: my-orm-py
Version: 1.2
Summary: Uma ORM simples para facilitar a implementação de SQL com Python
License: MIT
Author: paulindavzl
Author-email: paulochz01@gmail.com
Requires-Python: >=3.13,<4.0
Classifier: License :: OSI Approved :: MIT License
Classifier: Programming Language :: Python :: 3
Classifier: Programming Language :: Python :: 3.13
Requires-Dist: db-sqlite3 (>=0.0.1,<0.0.2)
Requires-Dist: mysql-connector-python (>=9.1.0,<10.0.0)
Requires-Dist: pg8000 (>=1.31.2,<2.0.0)
Requires-Dist: pytest (>=8.3.4,<9.0.0)
